grafannotate/__init__.py
grafannotate/annotation.py
grafannotate/cli.py
grafannotate-0.3.0.dist-info/LICENSE
grafannotate-0.3.0.dist-info/METADATA
grafannotate-0.3.0.dist-info/WHEEL
grafannotate-0.3.0.dist-info/entry_points.txt
grafannotate-0.3.0.dist-info/top_level.txt
grafannotate-0.3.0.dist-info/RECORD
