Metadata-Version: 2.1
Name: grafannotate
Version: 0.3.0
Summary: Send annotations to Grafana
Home-page: https://github.com/devopsmakers/python-grafannotate
Author: Tim Birkett
Author-email: tim.birkett@devopsmakers.com
License: MIT
Platform: any
Classifier: Development Status :: 5 - Production/Stable
Classifier: Topic :: Utilities
Classifier: Environment :: Console
Classifier: Intended Audience :: Information Technology
Classifier: Intended Audience :: System Administrators
Classifier: License :: OSI Approved :: MIT License
Classifier: Operating System :: OS Independent
Classifier: Programming Language :: Python
Classifier: Programming Language :: Python :: 3
Requires-Dist: click (==7.0)
Requires-Dist: requests (==2.22.0)
Requires-Dist: influxdb (==5.2.3)
